{"chunks": [{"chunk_bytes": 984050, "chunk_size": 3992, "dim": null, "filename": "gred_affinity_cleaned_08_05_2025_split_08_22_2025_test.parquet"}], "config": {"chunk_bytes": null, "chunk_size": null, "compression": null, "data_format": ["string", "string", "double", "double", "double", "string", "double", "double", "double", "double", "double", "double", "double", "double", "double", "double", "double", "string", "string", "string", "string", "string", "string", "string", "double", "string", "string", "string", "string", "string", "string", "string", "string", "string", "string", "string", "string", "double", "string", "int64", "string", "string", "string", "string", "int64", "string", "string", "string", "string", "string", "string", "string", "string", "int64", "int64", "bool", "bool", "int64", "int64", "bool", "bool", "bool", "bool", "bool"], "data_spec": null, "encryption": null, "item_loader": "ParquetLoader"}, "updated_at": "1757974476.9717226"}